sphinxcontrib/__init__.py
sphinxcontrib/playground.py
sphinxcontrib_playground-0.1.4.dist-info/LICENSE
sphinxcontrib_playground-0.1.4.dist-info/METADATA
sphinxcontrib_playground-0.1.4.dist-info/WHEEL
sphinxcontrib_playground-0.1.4.dist-info/top_level.txt
sphinxcontrib_playground-0.1.4.dist-info/zip-safe
sphinxcontrib_playground-0.1.4.dist-info/RECORD
