Metadata-Version: 2.1
Name: sphinxcontrib-playground
Version: 0.1.4
Summary: A Sphinx extension for embedding interactive demo     using The Python Playground
Home-page: https://github.com/ydcjeff/sphinxcontrib-playground
Author: Jeff Yang
Author-email: ydcjeff@gmail.com
License: MIT
Download-URL: https://pypi.org/project/sphinxcontrib-playground/#files
Project-URL: Documentation, https://ydcjeff.github.io/sphinxcontrib-playground
Project-URL: Source Code, https://github.com/ydcjeff/sphinxcontrib-playground
Project-URL: Bug Tracker, https://github.com/ydcjeff/sphinxcontrib-playground/issues
Project-URL: Changelog, https://github.com/ydcjeff/sphinxcontrib-playground/blob/main/CHANGELOG.md
Keywords: python,sphinx,playground,documentation
Platform: UNKNOWN
Classifier: Development Status :: 4 - Beta
Classifier: Environment :: Plugins
Classifier: Framework :: Sphinx
Classifier: Framework :: Sphinx :: Extension
Classifier: Intended Audience :: Developers
Classifier: Intended Audience :: Education
Classifier: Intended Audience :: Information Technology
Classifier: Intended Audience :: Science/Research
Classifier: License :: OSI Approved :: MIT License
Classifier: Operating System :: OS Independent
Classifier: Programming Language :: Python :: 3
Classifier: Topic :: Documentation
Classifier: Topic :: Documentation :: Sphinx
Classifier: Topic :: Utilities
Requires-Python: >=3.6
License-File: LICENSE
Requires-Dist: sphinx
Provides-Extra: dev
Requires-Dist: pytest ; extra == 'dev'
Requires-Dist: pytest-cov ; extra == 'dev'
Requires-Dist: yapf ; extra == 'dev'
Requires-Dist: pylint ; extra == 'dev'
Requires-Dist: isort ; extra == 'dev'
Requires-Dist: flake8 ; extra == 'dev'
